README.md
setup.py
standard/__init__.py
standard/standard.py
standard.egg-info/PKG-INFO
standard.egg-info/SOURCES.txt
standard.egg-info/dependency_links.txt
standard.egg-info/requires.txt
standard.egg-info/top_level.txt